{"stat.flyOneCm":12949,"stat.walkOneCm":5287,"stat.jump":51,"stat.playOneMinute":3186,"stat.useItem.minecraft.wooden_sword":4,"stat.pickup.minecraft.beef":8,"stat.leaveGame":1,"stat.sneakTime":5,"stat.damageTaken":43,"stat.pickup.minecraft.leather":2,"stat.damageDealt":430,"stat.pickup.minecraft.porkchop":5,"stat.timeSinceDeath":3186,"stat.useItem.minecraft.wooden_axe":6,"stat.killEntity.Cow":3,"stat.sprintOneCm":10710,"stat.mobKills":5,"stat.killEntity.Pig":2,"achievement.exploreAllBiomes":{"value":0,"progress":["Beach","Forest","Ocean","River","Plains"]}}